agentuniverse/__init__.py
agentuniverse/agent/__init__.py
agentuniverse/agent/action/__init__.py
agentuniverse/agent/action/knowledge/__init__.py
agentuniverse/agent/action/knowledge/doc_processor/__init__.py
agentuniverse/agent/action/knowledge/doc_processor/character_text_splitter.py
agentuniverse/agent/action/knowledge/doc_processor/character_text_splitter.yaml
agentuniverse/agent/action/knowledge/doc_processor/code_ast_processor.py
agentuniverse/agent/action/knowledge/doc_processor/dashscope_reranker.py
agentuniverse/agent/action/knowledge/doc_processor/dashscope_reranker.yaml
agentuniverse/agent/action/knowledge/doc_processor/doc_processor.py
agentuniverse/agent/action/knowledge/doc_processor/doc_processor_manager.py
agentuniverse/agent/action/knowledge/doc_processor/hierarchical_regex_text_spliter.py
agentuniverse/agent/action/knowledge/doc_processor/jieba_keyword_extractor.py
agentuniverse/agent/action/knowledge/doc_processor/jieba_keyword_extractor.yaml
agentuniverse/agent/action/knowledge/doc_processor/recursive_character_text_splitter.py
agentuniverse/agent/action/knowledge/doc_processor/recursive_character_text_splitter.yaml
agentuniverse/agent/action/knowledge/doc_processor/token_text_splitter.py
agentuniverse/agent/action/knowledge/doc_processor/token_text_splitter.yaml
agentuniverse/agent/action/knowledge/doc_processor/types/__init__.py
agentuniverse/agent/action/knowledge/doc_processor/types/ast_types.py
agentuniverse/agent/action/knowledge/doc_processor/types/code_types.py
agentuniverse/agent/action/knowledge/doc_processor/types/metrics_types.py
agentuniverse/agent/action/knowledge/embedding/__init__.py
agentuniverse/agent/action/knowledge/embedding/azureopenai_embedding.py
agentuniverse/agent/action/knowledge/embedding/azureopenai_embedding.yaml
agentuniverse/agent/action/knowledge/embedding/dashscope_embedding.py
agentuniverse/agent/action/knowledge/embedding/dashscope_embedding.yaml
agentuniverse-0.0.18.dist-info/LICENSE
agentuniverse-0.0.18.dist-info/METADATA
agentuniverse-0.0.18.dist-info/WHEEL
agentuniverse-0.0.18.dist-info/RECORD
